<?xml version="1.0" encoding="UTF-8"?>
<Customers xmlns="http://www.nrf-arts.org/IXRetail/namespace/"
                xmlns:dtv="http://www.datavantagecorp.com/xstore/"
                xmlns:xs="http://www.w3.org/2001/XMLSchema-instance"
                schemaLocation="http://www.nrf-arts.org/IXRetail/namespace/ Customers.xsd"
                dtv:schemaLocation="http://www.datavantagecorp.com/xstore/ DtvCustomers.xsd">
<Customer >
<DateTime><![CDATA[Wed Oct 23 14:21:56 CDT 2024]]></DateTime>
<CustomerID><![CDATA[C0110001000004]]></CustomerID>
<AlternateID><![CDATA[110001000003]]></AlternateID>
<ActiveFlag><![CDATA[true]]></ActiveFlag>
<CustomerAccount>
</CustomerAccount>
<Affiliation>
<Name><![CDATA[SignUpRetailLocation]]></Name>
<AffiliationType><![CDATA[dtv:SignUpRetailLocation]]></AffiliationType>
<RetailStoreID><![CDATA[619]]></RetailStoreID>
</Affiliation>
<Affiliation>
<Name><![CDATA[AllegianceRetailLocation]]></Name>
<AffiliationType><![CDATA[dtv:AllegianceRetailLocation]]></AffiliationType>
<RetailStoreID><![CDATA[619]]></RetailStoreID>
</Affiliation>
<EntityInformation PartyType="Individual">
<Individual>
<Name>
<Name Location="First"><![CDATA[Ajeet]]></Name>
<Name Location="Last"><![CDATA[Singh]]></Name>
</Name>
<PersonalSummary>
<Date><![CDATA[Wed Oct 23 14:21:56 CDT 2024]]></Date>
<Ethnicity></Ethnicity>
<MaritialStatusCode></MaritialStatusCode>
</PersonalSummary>
<ContactInformation>
<Telephone PrimaryFlag="false" TypeCode="HOME">
<FullTelephoneNumber><![CDATA[6266160842]]></FullTelephoneNumber>
<dtv:ContactFlag><![CDATA[false]]></dtv:ContactFlag>
</Telephone>
<Address PrimaryFlag="true" TypeCode="HOME">
<AddressLine1><![CDATA[16262 BEDFORD FALLS LN]]></AddressLine1>
<City><![CDATA[FRISCO]]></City>
<Territory><![CDATA[TX]]></Territory>
<PostalCode><![CDATA[75033-5919]]></PostalCode>
<Country><![CDATA[US]]></Country>
<dtv:Contact><![CDATA[true]]></dtv:Contact>
</Address>
<EmailReceiptsFlag><![CDATA[false]]></EmailReceiptsFlag>
</ContactInformation>
</Individual>
</EntityInformation>
<dtv:EnrollDate><![CDATA[2024-10-23]]></dtv:EnrollDate>
<dtv:AnniversaryDate><![CDATA[2024-10-23]]></dtv:AnniversaryDate>
<dtv:MailingListFlag><![CDATA[true]]></dtv:MailingListFlag>
</Customer>

</Customers>