<?xml version="1.0" encoding="UTF-8" standalone="yes"?>
<ns2:AvailabilityUpdate xmlns:ns2="http://microsretail.com/Locate">
    <ns2:availability_update_request_message>
        <message_header>
            <datetime>2024-10-21T14:35:49.039-05:00</datetime>
            <version>16.0</version>
            <source>XSTORE</source>
            <destination>Locate</destination>
        </message_header>
        <message_body>
            <system_cd>XSTORE</system_cd>
            <items>
                <item item_id="1015" qty="1" location_cd="110" method="DEC"/>
            </items>
        </message_body>
    </ns2:availability_update_request_message>
</ns2:AvailabilityUpdate>
